my_mess_proj_server-0.0.6.data/scripts/server_run.py
server/__init__.py
server/launcher.py
server/server.py
server/server_run.py
server/common/__init__.py
server/common/decor.py
server/common/deskriptors.py
server/common/errors.py
server/common/metaclases.py
server/common/utils.py
server/common/variables.py
server/doc/__init__.py
server/doc/source/__init__.py
server/doc/source/conf.py
server/logs/__init__.py
server/logs/config_client_log.py
server/logs/config_server_log.py
server/server/__init__.py
server/server/add_user.py
server/server/config_window.py
server/server/core.py
server/server/database.py
server/server/main_window.py
server/server/remove_user.py
server/server/stat_window.py
server/unit_tests/__init__.py
server/unit_tests/test_client.py
server/unit_tests/test_server.py
server/unit_tests/test_utils.py
my_mess_proj_server-0.0.6.dist-info/METADATA
my_mess_proj_server-0.0.6.dist-info/WHEEL
my_mess_proj_server-0.0.6.dist-info/top_level.txt
my_mess_proj_server-0.0.6.dist-info/RECORD
