Metadata-Version: 2.1
Name: my-mess-proj-server
Version: 0.0.6
Summary: my_mess_proj_server
Home-page: UNKNOWN
Author: Sergey Petin
Author-email: pillager@bk.ru
License: UNKNOWN
Platform: UNKNOWN
Requires-Dist: PyQt5
Requires-Dist: sqlalchemy
Requires-Dist: pycryptodomex
